Workbook

Sheet VisionPitts Summary
A1: VisionPitts master data list — summary
A2: Counts update automatically from the 'Data Catalog' sheet (columns O–P). Updated 2026-09-26.
A4: VisionPitts status | B4: Organizers' catalog | C4: Added by VisionPitts | D4: Total
A5: In use | B5: =COUNTIFS('Data Catalog'!$P$2:$P$107,$A5,'Data Catalog'!$O$2:$O$107,"Organizers' catalog") -> 14 | C5: =COUNTIFS('Data Catalog'!$P$2:$P$107,$A5,'Data Catalog'!$O$2:$O$107,"Added by VisionPitts") -> 22 | D5: =SUM(B5:C5) -> 36
A6: Partial | B6: =COUNTIFS('Data Catalog'!$P$2:$P$107,$A6,'Data Catalog'!$O$2:$O$107,"Organizers' catalog") -> 6 | C6: =COUNTIFS('Data Catalog'!$P$2:$P$107,$A6,'Data Catalog'!$O$2:$O$107,"Added by VisionPitts") -> 0 | D6: =SUM(B6:C6) -> 6
A7: On disk (unused) | B7: =COUNTIFS('Data Catalog'!$P$2:$P$107,$A7,'Data Catalog'!$O$2:$O$107,"Organizers' catalog") -> 0 | C7: =COUNTIFS('Data Catalog'!$P$2:$P$107,$A7,'Data Catalog'!$O$2:$O$107,"Added by VisionPitts") -> 1 | D7: =SUM(B7:C7) -> 1
A8: Verified, not ingested | B8: =COUNTIFS('Data Catalog'!$P$2:$P$107,$A8,'Data Catalog'!$O$2:$O$107,"Organizers' catalog") -> 11 | C8: =COUNTIFS('Data Catalog'!$P$2:$P$107,$A8,'Data Catalog'!$O$2:$O$107,"Added by VisionPitts") -> 23 | D8: =SUM(B8:C8) -> 34
A9: Not yet | B9: =COUNTIFS('Data Catalog'!$P$2:$P$107,$A9,'Data Catalog'!$O$2:$O$107,"Organizers' catalog") -> 25 | C9: =COUNTIFS('Data Catalog'!$P$2:$P$107,$A9,'Data Catalog'!$O$2:$O$107,"Added by VisionPitts") -> 0 | D9: =SUM(B9:C9) -> 25
A10: Not relevant | B10: =COUNTIFS('Data Catalog'!$P$2:$P$107,$A10,'Data Catalog'!$O$2:$O$107,"Organizers' catalog") -> 4 | C10: =COUNTIFS('Data Catalog'!$P$2:$P$107,$A10,'Data Catalog'!$O$2:$O$107,"Added by VisionPitts") -> 0 | D10: =SUM(B10:C10) -> 4
A11: Total | B11: =SUM(B5:B10) -> 60 | C11: =SUM(C5:C10) -> 46 | D11: =SUM(D5:D10) -> 106
A13: Share of all sources in use | B13: =IF(D11=0,0,D5/D11) -> 0.33962264
A14: Sources in use or partial | B14: =D5+D6 -> 42
A16: Status key | B16: In use = feeds the dashboard or a built layer · Partial = partly used or a substitute is used · On disk (unused) = downloaded but not used · Verified, not ingested = link checked live 2026-09-24/26, ready for the data terminal · Not yet = not investigated · Not relevant = outside Track 3 scope.
A17: Where detail lives | B17: Pipeline registry: data/sources.md · Built layers: 'VisionPitts Layers' sheet and handoff/web-claude/DELIVERED.md · Discovery (~200 sources): docs/data/discovery/DATA_DISCOVERY.md · Files on disk: handoff/web-claude/INVENTORY.md.
A18: Original file | B18: The organizers' version is preserved at data/raw/AI Hackathon for Housing — Public Data Catalog (original 2026-09-26).xlsx.

Sheet Data Catalog
A1: Priority | B1: Category | C1: Data source | D1: Provider / steward | E1: Provider type | F1: Geographic coverage | G1: Granularity | H1: Access / format | I1: Typical update | J1: Primary hackathon uses | K1: Relevant problem briefs | L1: Likely join key | M1: URL | N1: Caveats / licensing notes | O1: Origin | P1: VisionPitts status | Q1: Local path / output | R1: Vintage in use | S1: Tract-level? | T1: VisionPitts notes
A2: Core | B2: Property & parcels | C2: Allegheny County Property Assessments | D2: Allegheny County / WPRDC | E2: Public | F2: Allegheny County | G2: Parcel | H2: Open download; CSV/API | I2: Daily/periodic | J2: Parcel characteristics, assessed land/building values, exemptions, feasibility screening | K2: Feasibility; Typology & Climate | L2: Block and lot / parcel ID | M2: https://data.wprdc.org/dataset/property-assessments | N2: Assessment fields can be stale or missing; do not treat assessed value as market value. | O2: Organizers' catalog | P2: In use | Q2: data/external/parcels/assessments.csv | R2: 2026 | S2: via parcel join | T2: STORIES/YEARBLT drive 3D building heights (fetch_buildings.py).
A3: Core | B3: Property & parcels | C3: Allegheny County Property Sale Transactions | D3: Allegheny County / WPRDC | E3: Public | F3: Allegheny County | G3: Transaction / parcel | H3: Open download; CSV/API | I3: Daily | J3: Comparable sales, price trends, calibration, neighborhood demand | K3: Feasibility; Observatory | L3: Parcel ID; sale date; deed reference | M3: https://data.wprdc.org/dataset/allegheny-county-property-sale-transactions | N3: Filter using sale-validation codes; many nominal transfers are not arm’s-length sales. | O3: Organizers' catalog | P3: Verified, not ingested | S3: via parcel join | T3: 99,176 arm's-length (VALID SALE) records 2012–2026; P1 price-trend signal.
A4: Core | B4: Property & parcels | C4: Allegheny County Parcel Boundaries | D4: Allegheny County GIS / WPRDC | E4: Public | F4: Allegheny County | G4: Parcel polygon | H4: Open GIS download; GeoJSON/SHP/API | I4: Periodic | J4: Map parcels, calculate lot area, spatially join zoning and hazards | K4: All briefs | L4: Parcel ID | M4: https://data.wprdc.org/dataset/allegheny-county-parcel-boundaries | N4: Geometry and assessment records may update on different schedules; validate parcel IDs. | O4: Organizers' catalog | P4: In use | Q4: data/external/parcels/alleghenycounty_parcels202609.geojson | R4: 2026-09 | S4: via spatial join | T4: Building → parcel → assessment join for heights.
A5: Core | B5: Property & parcels | C5: Allegheny County GIS Open Data Portal | D5: Allegheny County | E5: Public | F5: Allegheny County | G5: Varies: parcel to county | H5: ArcGIS Hub downloads and services | I5: Varies | J5: Discover authoritative county boundaries, land use, infrastructure, hazards, and administrative layers | K5: All briefs | L5: Parcel ID; GEOID; spatial join | M5: https://openac-alcogis.opendata.arcgis.com/ | N5: Portal is a catalog; inspect metadata and update dates for each layer. | O5: Organizers' catalog | P5: Not yet | S5: varies | T5: Catalog portal; individual layers listed separately.
A6: Core | B6: Permits & development | C6: PLI Permits | D6: City of Pittsburgh / WPRDC | E6: Public | F6: City of Pittsburgh | G6: Permit / address | H6: Open download; CSV/GeoJSON/API | I6: Daily | J6: Project pipeline, permit type, status, processing-time analysis | K6: Feasibility; Permit Navigator; Observatory | L6: Address; parcel ID where available; permit ID | M6: https://data.wprdc.org/dataset/pli-permits | N6: Current series begins in 2019; project-level unit counts may require parsing or linkage. | O6: Organizers' catalog | P6: In use | Q6: data/processed/permits.parquet, permits_by_year.parquet | R6: 2019-06 → 2026 | S6: yes (point-in-tract) | T6: D8: new-residential and demolition permits by tract-year; city only; no unit-count field.
A7: Core | B7: Permits & development | C7: Historical PLI Permits | D7: City of Pittsburgh / WPRDC | E7: Public | F7: City of Pittsburgh | G7: Permit / address | H7: Open download; spreadsheet | I7: Historical archive | J7: Long-run permitting trends and before/after policy comparisons | K7: Permit Navigator; Observatory | L7: Address; permit ID | M7: https://data.wprdc.org/dataset/pli-permits | N7: Older records use different schemas and may need normalization. | O7: Organizers' catalog | P7: Not yet | S7: no | T7: Monthly summaries 2015–18 not joinable to tracts.
A8: Core | B8: Permits & development | C8: PLI / DOMI / Environmental Services Violations | D8: City of Pittsburgh / WPRDC | E8: Public | F8: City of Pittsburgh | G8: Violation / address | H8: Open download; CSV/GeoJSON | I8: Daily | J8: Property condition, code-enforcement patterns, completeness and risk flags | K8: Feasibility; Permit Navigator; Observatory | L8: Address; parcel ID where available | M8: https://data.wprdc.org/dataset/pittsburgh-pli-violations-report | N8: Multiple departments share the feed; interpret status and closure fields carefully. | O8: Organizers' catalog | P8: Not yet | S8: via address/parcel
A9: Useful | B9: Permits & development | C9: Condemned and Dead-End Properties | D9: City of Pittsburgh / WPRDC | E9: Public | F9: City of Pittsburgh | G9: Property / address | H9: Open download; CSV/GeoJSON | I9: Frequent | J9: Identify distressed stock, redevelopment candidates, and ownership barriers | K9: Feasibility; Observatory | L9: Address; parcel ID | M9: https://data.wprdc.org/dataset/condemned-properties | N9: Condemnation does not establish demolition feasibility or site availability. | O9: Organizers' catalog | P9: Verified, not ingested | S9: via parcel | T9: Distress signal for 'stabilize failing stock' list (P1).
A10: Core | B10: Zoning & policy | C10: Pittsburgh Zoning Districts | D10: City of Pittsburgh / WPRDC | E10: Public | F10: City of Pittsburgh | G10: Zoning polygon | H10: Open GIS download; CSV/GeoJSON/SHP | I10: Periodic | J10: Determine base zoning and spatially screen allowed development | K10: Feasibility; Permit Navigator; Typology & Climate | L10: Spatial join; zoning code | M10: https://data.wprdc.org/dataset/pittsburgh-zoning | N10: Map alone is insufficient: overlays, definitions, exceptions, and review rules matter. | O10: Organizers' catalog | P10: Verified, not ingested | R10: current (edited 2026-09-22) | S10: via area share | T10: P0: fills 'Can it be built here?'; 1,069 polygons; draft district→typology matrix in docs/data/discovery/01.
A11: Core | B11: Zoning & policy | C11: Pittsburgh Zoning Code | D11: City of Pittsburgh | E11: Public | F11: City of Pittsburgh | G11: Legal text / section | H11: Public website | I11: As amended | J11: Retrieve and cite permitted uses, dimensional standards, parking, reviews, and definitions | K11: Feasibility; Permit Navigator; Typology & Climate | L11: Zoning district; section number | M11: https://pittsburghpa.gov/dcp/zoning-code | N11: Authoritative interpretation belongs to the City; models must cite sections and flag ambiguity. | O11: Organizers' catalog | P11: Partial | Q11: docs/data/discovery/01_land_zoning_development.md | R11: Use Table §911.02 (2024) | S11: n/a | T11: Draft typology permissions with citations; City Zoning Administrator is authoritative. Bill 2025-1545 (ADU by right) pending.
A12: Useful | B12: Zoning & policy | C12: Pittsburgh Zoning Board of Adjustment Decisions | D12: City of Pittsburgh | E12: Public | F12: City of Pittsburgh | G12: Case / parcel / decision | H12: Public agendas, decisions, and records | I12: Ongoing | J12: Train retrieval tools; identify common variances, conditions, and bottlenecks | K12: Feasibility; Permit Navigator | L12: Case number; address; parcel ID | M12: https://pittsburghpa.gov/dcp/zba | N12: Documents may be PDFs and inconsistent over time; outcomes require careful extraction. | O12: Organizers' catalog | P12: Not yet | S12: no
A13: Useful | B13: Zoning & policy | C13: Pennsylvania Municipal Codes | D13: General Code / municipal publishers | E13: Private publisher, public access | F13: Pennsylvania municipalities | G13: Municipal code / section | H13: Public web access | I13: Varies by municipality | J13: Compare zoning and permitting requirements across Allegheny County jurisdictions | K13: Permit Navigator; Typology & Climate | L13: Municipality; chapter; section | M13: https://www.generalcode.com/library/pa | N13: Coverage and update timing vary; some municipalities use other publishers or PDF ordinances. | O13: Organizers' catalog | P13: Not yet | S13: no | T13: No county-wide compiled zoning layer exists; suburbs shown as 'municipal ordinance, not scored'.
A14: Core | B14: Housing production | C14: Pittsburgh Development / Permit Records via OneStopPGH | D14: City of Pittsburgh | E14: Public | F14: City of Pittsburgh | G14: Application / permit / address | H14: Public search portal | I14: Ongoing | J14: Validate current case status and inspect project documents | K14: Feasibility; Permit Navigator; Observatory | L14: Application number; address | M14: https://onestoppgh.pittsburghpa.gov/ | N14: Interactive portal is not necessarily suitable for bulk extraction; respect terms and rate limits. | O14: Organizers' catalog | P14: Not yet | S14: no | T14: Portal; not for bulk extraction.
A15: Useful | B15: Housing production | C15: City-Owned Properties | D15: City of Pittsburgh / WPRDC | E15: Public | F15: City of Pittsburgh | G15: Parcel / property | H15: Open download; CSV/XLSX | I15: Periodic | J15: Public-land pipeline, redevelopment opportunities, disposition analysis | K15: Feasibility; Observatory | L15: Parcel ID; address | M15: https://data.wprdc.org/dataset/city-owned-properties | N15: Ownership and availability are different; verify disposition status. | O15: Organizers' catalog | P15: Verified, not ingested | S15: via parcel | T15: 11,375 City-owned vacant parcels in City parcel layer (P0 land-supply).
A16: Useful | B16: Housing production | C16: City of Pittsburgh Property Tax Abatements | D16: City of Pittsburgh / WPRDC | E16: Public | F16: City of Pittsburgh | G16: Property / abatement | H16: Open download; CSV/XLSX | I16: Periodic | J16: Map incentives, estimate policy reach, link to production outcomes | K16: Feasibility; Observatory | L16: Parcel ID; address | M16: https://data.wprdc.org/dataset/city-of-pittsburgh-property-tax-abatements | N16: Program rules and valuation fields can change; distinguish approval from realized benefit. | O16: Organizers' catalog | P16: Not yet | S16: via parcel
A17: Core | B17: Regional housing needs | C17: Allegheny County Housing Needs Assessment | D17: Allegheny County | E17: Public | F17: Allegheny County; 13 subregions | G17: Subregion / indicator | H17: Public report and data products | I17: Periodic | J17: Baseline needs, affordability, demand, supply gaps, and equity context | K17: Observatory; Typology & Climate | L17: Subregion; municipality | M17: https://www.alleghenycounty.us/Services/Housing/Housing-Needs-Assessment | N17: Useful baseline but too aggregated for parcel-level prototypes; document vintage. | O17: Organizers' catalog | P17: Not yet | S17: no | T17: County's first HNA ordered by Feb 2026 'Housing for All' EO; City HNA 2022 exists.
A18: Core | B18: Demographics & housing | C18: American Community Survey 5-Year | D18: U.S. Census Bureau | E18: Public | F18: United States | G18: Block group, tract, place, county and more | H18: API and downloads | I18: Annual | J18: Income, household size, tenure, rent, value, vacancy, commuting, demographics | K18: Observatory; Typology & Climate | L18: GEOID | M18: https://www.census.gov/data/developers/data-sets/acs-5year.html | N18: Estimates have margins of error; avoid false precision for small areas. | O18: Organizers' catalog | P18: In use | Q18: data/processed/tracts_acs.parquet; profile_change.parquet | R18: 2020–24 and 2009–13 vs 2019–23 | S18: yes | T18: Context stats with MOE/CV; D8 ten-year change with significance flags.
A19: Core | B19: Demographics & housing | C19: Decennial Census | D19: U.S. Census Bureau | E19: Public | F19: United States | G19: Block to nation | H19: API and downloads | I19: Every 10 years | J19: Population, households, occupancy, race/ethnicity, baseline small-area counts | K19: Observatory; Typology & Climate | L19: GEOID | M19: https://www.census.gov/programs-surveys/decennial-census/data.html | N19: Limited socioeconomic detail compared with ACS; geography changes complicate time series. | O19: Organizers' catalog | P19: In use | Q19: data/external/crosswalks/tiger/tl_2020_42_tabblock20.zip | R19: 2020 | S19: yes | T19: Block HOUSING20 for crosswalk weights; DHC H4 renter units for eviction ZIP→tract spread.
A20: Core | B20: Geographic reference | C20: TIGER/Line Shapefiles | D20: U.S. Census Bureau | E20: Public | F20: United States | G20: Blocks, tracts, roads, places and more | H20: Shapefile downloads | I20: Annual | J20: Geographic boundaries and crosswalks for Census and administrative data | K20: All briefs | L20: GEOID | M20: https://www.census.gov/geographies/mapping-files/time-series/geo/tiger-line-file.html | N20: Boundary vintages must match the statistics being joined. | O20: Organizers' catalog | P20: In use | Q20: data/external/boundaries/, tiger_cache/ | R20: 2023 (pinned), 2020, 2010 | S20: yes | T20: Tracts, BGs, places, PUMAs, county subdivisions, ZCTAs.
A21: Core | B21: Affordability | C21: Comprehensive Housing Affordability Strategy (CHAS) | D21: HUD | E21: Public | F21: United States | G21: Custom geography; tract for selected tables | H21: Downloads / query tools | I21: Periodic | J21: Cost burden, housing problems, tenure, household type, and HUD income bands | K21: Observatory; Typology & Climate | L21: GEOID | M21: https://www.huduser.gov/portal/datasets/cp.html | N21: Based on multi-year ACS data; releases lag and tables are complex. | O21: Organizers' catalog | P21: In use | Q21: data/external/benchmark/chas/table8_42003.parquet | R21: 2018–22 | S21: yes | T21: Table 8 → need (renters ≤50% AMI) and cost burden in displacement risk.
A22: Useful | B22: Affordability | C22: Location Affordability Index | D22: HUD / DOT | E22: Public | F22: United States | G22: Block group / tract | H22: Open GIS download | I22: Periodic | J22: Combined housing and transportation cost scenarios | K22: Typology & Climate; Observatory | L22: GEOID | M22: https://hudgis-hud.opendata.arcgis.com/datasets/c1c32742599a42c9a45c95be50ed2ab6_12/about | N22: Modeled estimates depend on household profiles and vintage; not observed household spending. | O22: Organizers' catalog | P22: Not yet | S22: yes | T22: Track 3 core gap (transport cost / carbon story).
A23: Core | B23: Affordability | C23: Fair Market Rents and Small Area FMRs | D23: HUD | E23: Public | F23: United States | G23: Metro / county; ZIP for SAFMR | H23: Downloads / API | I23: Annual | J23: Rent benchmarks, voucher payment standards, preliminary pro formas | K23: Feasibility; Observatory | L23: FIPS; ZIP | M23: https://www.huduser.gov/portal/datasets/fmr.html | N23: Regulatory benchmarks, not direct measures of asking or contract rents. | O23: Organizers' catalog | P23: In use | Q23: web/src/data/income_limits.json | R23: FY2026 | S23: metro | T23: D4: 2BR FMR $1,299 (Pittsburgh HMFA).
A24: Useful | B24: Affordability | C24: HUD Income Limits | D24: HUD | E24: Public | F24: United States | G24: Metro / county / family size | H24: Downloads / API | I24: Annual | J24: Affordable-rent calculations and household eligibility thresholds | K24: Feasibility; Typology & Climate | L24: HUD area; family size | M24: https://www.huduser.gov/portal/datasets/il.html | N24: Use the correct program year and household-size adjustment. | O24: Organizers' catalog | P24: In use | Q24: web/src/data/income_limits.json | R24: FY2026 | S24: metro | T24: D4: 50% AMI $55,200 (family of 4); MFI $110,400.
A25: Core | B25: Subsidized housing | C25: Low-Income Housing Tax Credit Database | D25: HUD | E25: Public | F25: United States | G25: Project / building | H25: Downloadable database and GIS | I25: Periodic | J25: Locate LIHTC stock, placed-in-service dates, units, and preservation needs | K25: Observatory; Typology & Climate | L25: Project ID; address; coordinates | M25: https://www.huduser.gov/portal/datasets/lihtc.html | N25: Some project attributes and geocodes are missing or approximate. | O25: Organizers' catalog | P25: Verified, not ingested | R25: HUD layer (no PIS after 2019) | S25: via point | T25: 215 Allegheny projects, 7,378 LI units; P0 existing affordable stock layer.
A26: Useful | B26: Subsidized housing | C26: National Housing Preservation Database | D26: Public and Affordable Housing Research Corporation / NLIHC | E26: Nonprofit, public registration | F26: United States | G26: Subsidized property | H26: Download after registration | I26: Periodic | J26: Preservation risk, subsidy expirations, affordable housing inventory | K26: Observatory; Typology & Climate | L26: NHPD property ID; address | M26: https://preservationdatabase.org/ | N26: Free access may require registration and agreement to terms. | O26: Organizers' catalog | P26: Not yet | S26: via point | T26: Registration required.
A27: Useful | B27: Vacancy & distress | C27: USPS Vacancy Data | D27: HUD / USPS | E27: Public with conditions | F27: United States | G27: Census tract | H27: Download / mapping tools | I27: Quarterly | J27: Residential vacancy, no-stat addresses, neighborhood distress | K27: Observatory; Typology & Climate | L27: GEOID | M27: https://www.huduser.gov/portal/datasets/usps.html | N27: Aggregated and subject to suppression; “vacant” is a postal-status concept. | O27: Organizers' catalog | P27: Verified, not ingested | R27: 2023 quarterly | S27: yes | T27: WPRDC mirror on 2020 tracts (394/394), no HUD login needed.
A28: Core | B28: Mortgage & finance | C28: Home Mortgage Disclosure Act Data | D28: CFPB / FFIEC | E28: Public | F28: United States | G28: Mortgage application / loan | H28: Bulk download and API | I28: Annual | J28: Loan approvals, denials, borrower characteristics, loan types, lender patterns | K28: Feasibility; Observatory | L28: Census tract GEOID; lender; year | M28: https://ffiec.cfpb.gov/data-publication/ | N28: Protected fields are modified; analysis must be careful about fair-lending interpretation. | O28: Organizers' catalog | P28: Not yet | S28: yes | T28: P1: tract investor share, denial rates.
A29: Useful | B29: Jobs & mobility | C29: LEHD Origin-Destination Employment Statistics (LODES) | D29: U.S. Census Bureau | E29: Public | F29: United States | G29: Census block / flow | H29: Bulk download | I29: Annual | J29: Home-to-work flows, employment access, job density, commute patterns | K29: Observatory; Typology & Climate | L29: Census block GEOID | M29: https://lehd.ces.census.gov/data/ | N29: Data are modeled and noise-infused; latest year lags. | O29: Organizers' catalog | P29: In use | Q29: data/processed/opportunity_access.parquet | R29: LODES8 WAC 2023 | S29: yes (3 km radius) | T29: D2: jobs within 3 km (total, low-wage).
A30: Useful | B30: Jobs & economy | C30: Quarterly Census of Employment and Wages | D30: BLS | E30: Public | F30: United States | G30: County / industry | H30: Downloads and API | I30: Quarterly | J30: Employment and wage trends for demand and feasibility context | K30: Observatory; Typology & Climate | L30: County FIPS; NAICS | M30: https://www.bls.gov/cew/downloadable-data-files.htm | N30: Small cells may be suppressed; workplace location differs from residence. | O30: Organizers' catalog | P30: Not relevant | S30: no | T30: County/industry only.
A31: Useful | B31: Construction costs | C31: Producer Price Index | D31: BLS | E31: Public | F31: United States | G31: National industry / commodity index | H31: API and downloads | I31: Monthly | J31: Construction material and contractor-cost escalation scenarios | K31: Feasibility | L31: Series ID; month | M31: https://www.bls.gov/ppi/data.htm | N31: National indexes are not Pittsburgh bids; use as escalation factors, not level estimates. | O31: Organizers' catalog | P31: Not relevant | S31: no | T31: Construction cost (Track 1).
A32: Core | B32: Transit & accessibility | C32: Pittsburgh Regional Transit GTFS | D32: Pittsburgh Regional Transit / WPRDC | E32: Public | F32: Allegheny County region | G32: Stop, route, trip, schedule | H32: GTFS ZIP / open download | I32: Regular schedule updates | J32: Transit access, service frequency, travel-time and climate scoring | K32: Typology & Climate; Observatory | L32: Stop ID; route ID; spatial join | M32: https://data.wprdc.org/dataset/port-authority-of-allegheny-county-transit-data | N32: Scheduled service is not the same as realized reliability; agency name may appear historically as Port Authority. | O32: Organizers' catalog | P32: In use | Q32: data/external/benchmark/gtfs/prt_gtfs.zip | R32: 2026 feed | S32: yes | T32: transit_access factor: weekday departures ≤400 m per acre.
A33: Useful | B33: Transportation | C33: PennDOT Open Data | D33: PennDOT | E33: Public | F33: Pennsylvania | G33: Road segment, bridge, traffic count | H33: Open GIS and downloads | I33: Varies | J33: Road access, traffic volumes, bridge constraints, crash and infrastructure context | K33: Feasibility; Typology & Climate | L33: Route/segment ID; spatial join | M33: https://gis.penndot.gov/paprojects/ | N33: Different products have different download paths and vintages. | O33: Organizers' catalog | P33: Not yet | S33: no | T33: Low priority for scope.
A34: Useful | B34: Amenities & network | C34: OpenStreetMap | D34: OpenStreetMap contributors | E34: Nonprofit / crowdsourced | F34: Global | G34: Building, road, amenity, address and other features | H34: Open API and extracts | I34: Continuous | J34: Amenities, street network, buildings, walkability proxies, routing | K34: All briefs | L34: OSM ID; spatial join | M34: https://www.openstreetmap.org/ | N34: Completeness varies; comply with ODbL attribution and share-alike requirements. | O34: Organizers' catalog | P34: In use | Q34: data/external/opportunity_access/ (Overpass cache) | R34: OSM 2026-07-28 | S34: yes (800 m radius) | T34: D2 services within 800 m; OpenFreeMap basemap + 3D context; Photon/Nominatim geocoding. Under-maps childcare/pharmacies.
A35: Useful | B35: Address reference | C35: OpenAddresses | D35: Open Knowledge Foundation / contributors | E35: Nonprofit / mixed public sources | F35: Global | G35: Address point | H35: Open bulk download | I35: Varies | J35: Geocoding, address normalization, matching administrative records | K35: All briefs | L35: Normalized address; coordinates | M35: https://openaddresses.io/ | N35: Coverage and licensing vary by source; inspect source metadata. | O35: Organizers' catalog | P35: Not yet | S35: no | T35: Live geocoders used instead.
A36: Core | B36: Topography & imagery | C36: Pennsylvania Spatial Data Access (PASDA) | D36: Penn State Institutes of Energy and the Environment | E36: Public | F36: Pennsylvania | G36: Varies; parcel/vector/raster | H36: Open downloads and map services | I36: Varies | J36: LiDAR, imagery, parcels, mine and environmental layers for site screening | K36: Feasibility; Typology & Climate | L36: Spatial join; parcel ID where present | M36: https://www.pasda.psu.edu/ | N36: Catalog spans many vintages and stewards; inspect each layer’s metadata. | O36: Organizers' catalog | P36: Partial | S36: varies | T36: LiDAR/footprints reviewed; PEMA 2021–23 imagery tiles verified for a satellite toggle.
A37: Core | B37: Topography & imagery | C37: USGS 3D Elevation Program | D37: U.S. Geological Survey | E37: Public | F37: United States | G37: Raster elevation / point cloud | H37: Open download and services | I37: Periodic | J37: Slope, grading difficulty, drainage, viewshed, site constraints | K37: Feasibility; Typology & Climate | L37: Spatial join | M37: https://www.usgs.gov/3d-elevation-program | N37: Resolution and acquisition year vary by location. | O37: Organizers' catalog | P37: In use | Q37: research/musa6950_takeaway/data/dem/; data/processed/tract_terrain.parquet | R37: 1 arc-sec (2024 download) | S37: yes | T37: Tract elevation/slope (info only); Mapterhorn tiles (incl. 3DEP) for 3D terrain.
A38: Useful | B38: Topography & imagery | C38: Allegheny County Orthoimagery | D38: Allegheny County / PASDA | E38: Public | F38: Allegheny County | G38: High-resolution raster tiles | H38: Open download / map service | I38: Periodic flights | J38: Detect structures and land cover; validate parcel and building context | K38: Feasibility; Observatory | L38: Spatial join; tile index | M38: https://www.pasda.psu.edu/uci/SearchResults.aspx?Keyword=Allegheny%20County%20Imagery | N38: Large files; imagery date must be recorded and visual interpretation validated. | O38: Organizers' catalog | P38: Partial | Q38: research/musa6950_takeaway/data/naip/ | R38: NAIP 2022 | S38: yes (zonal) | T38: NAIP used for NDVI vegetation cover instead of county ortho.
A39: Core | B39: Hazards & environment | C39: FEMA National Flood Hazard Layer | D39: FEMA | E39: Public | F39: United States | G39: Flood zone polygon / line | H39: Open GIS services and downloads | I39: Ongoing revisions | J39: Floodplain screening, risk communication, feasibility and climate scoring | K39: Feasibility; Typology & Climate | L39: Spatial join; community/panel ID | M39: https://www.fema.gov/flood-maps/national-flood-hazard-layer | N39: Not a substitute for survey or flood determination; map amendments may matter. | O39: Organizers' catalog | P39: Verified, not ingested | R39: effective 2014-09-26 | S39: via area share | T39: P0: 7,793 Allegheny polygons; validate/replace HAND flood share; streamable raster.
A40: Useful | B40: Hazards & environment | C40: PA DEP eMapPA | D40: Pennsylvania DEP | E40: Public | F40: Pennsylvania | G40: Facility, permit, mine and environmental feature | H40: Interactive map / GIS services | I40: Varies | J40: Contamination, regulated facilities, mining, water and environmental constraints | K40: Feasibility; Typology & Climate | L40: Facility ID; permit ID; spatial join | M40: https://www.dep.pa.gov/DataandTools/Pages/eMapPA.aspx | N40: Multiple programs and vintages; confirm authoritative program records. | O40: Organizers' catalog | P40: Not yet | S40: varies | T40: Mined areas layer noted (1,004 polygons).
A41: Core | B41: Hazards & environment | C41: Pittsburgh Steep Slopes (25% or greater) | D41: City of Pittsburgh / WPRDC | E41: Public | F41: City of Pittsburgh | G41: Slope polygon | H41: Open GIS download | I41: Periodic | J41: Flag difficult or regulated sites and estimate grading risk | K41: Feasibility; Typology & Climate | L41: Spatial join | M41: https://data.wprdc.org/dataset/25-or-greater-slope | N41: Derived threshold layer; site engineering requires detailed survey/geotechnical work. | O41: Organizers' catalog | P41: Partial | Q41: data/processed/tract_terrain.parquet | R41: DEM-derived | S41: via area share | T41: We compute slope from 30 m DEM; official City ≥25% layer (1,714 polys) verified, not ingested.
A42: Core | B42: Hazards & environment | C42: Pittsburgh Undermined Areas | D42: City / County / WPRDC | E42: Public | F42: Pittsburgh / Allegheny County | G42: Mine influence polygon | H42: Open GIS download | I42: Periodic | J42: Preliminary mine-subsidence risk screening | K42: Feasibility; Typology & Climate | L42: Spatial join | M42: https://data.wprdc.org/dataset/undermined-areas | N42: Historic mine maps can be incomplete or imprecise; never use alone for safety decisions. | O42: Organizers' catalog | P42: Verified, not ingested | S42: via area share | T42: P0 constraint share (City 47 polys; PA DEP county 1,004).
A43: Useful | B43: Hazards & environment | C43: EPA EJScreen | D43: U.S. EPA | E43: Public | F43: United States | G43: Block group / tract indicators | H43: Open downloads and API/GIS | I43: Annual | J43: Environmental burden, demographic context, cumulative-impact screening | K43: Typology & Climate; Observatory | L43: GEOID | M43: https://www.epa.gov/ejscreen/download-ejscreen-data | N43: Screening tool, not a risk assessment; methods and indicator definitions change. | O43: Organizers' catalog | P43: Not relevant | S43: yes | T43: Taken offline 2025; replaced by PA DEP PennEnviroScreen (added below).
A44: Useful | B44: Land cover & heat | C44: National Land Cover Database | D44: Multi-Resolution Land Characteristics Consortium / USGS | E44: Public | F44: United States | G44: 30-meter raster and derivatives | H44: Open download | I44: Periodic | J44: Impervious surface, tree cover, green space, heat and runoff proxies | K44: Typology & Climate | L44: Spatial join | M44: https://www.mrlc.gov/data | N44: Resolution may miss parcel-scale features; record product year. | O44: Organizers' catalog | P44: Partial | Q44: research/musa6950_takeaway/outputs/tract_ndvi_flood.parquet | R44: NAIP 2022 NDVI | S44: yes | T44: NDVI vegetation cover instead of NLCD; impervious (NLCD 2021) P1.
A45: Useful | B45: Climate | C45: NOAA Climate Data Online | D45: NOAA | E45: Public | F45: United States | G45: Weather station / gridded products | H45: API and downloads | I45: Daily to annual | J45: Heat, precipitation, extreme-weather history, climate baselines | K45: Typology & Climate | L45: Station ID; coordinates; date | M45: https://www.ncei.noaa.gov/cdo-web/ | N45: Station coverage and missing observations require quality control. | O45: Organizers' catalog | P45: Not yet | S45: no
A46: Useful | B46: Energy & buildings | C46: ResStock Public Data | D46: U.S. Department of Energy / NREL | E46: Public | F46: United States | G46: Modeled residential building stock / scenarios | H46: Open downloads | I46: Periodic releases | J46: Energy use, retrofit, emissions and housing-type scenario assumptions | K46: Typology & Climate; Feasibility | L46: Geography; building archetype | M46: https://resstock.nrel.gov/ | N46: Modeled stock, not parcel-level observed energy use; document scenario vintage. | O46: Organizers' catalog | P46: Not yet | S46: no | T46: Track 3 core gap (carbon per typology).
A47: Core | B47: Private public data | C47: Zillow Research Housing Data | D47: Zillow | E47: Private company, public aggregate data | F47: United States | G47: Neighborhood, ZIP, city, county, metro, state | H47: Free CSV downloads | I47: Weekly/monthly depending on metric | J47: ZHVI values, ZORI rents, inventory, sales, affordability, demand trends | K47: Feasibility; Observatory; Typology & Climate | L47: Region name/ID; ZIP; county FIPS; date | M47: https://www.zillow.com/research/data/ | N47: Aggregate research data are public; listing-level/property-level data are not included. CSV URLs can change and historical values may be revised. | O47: Organizers' catalog | P47: Partial | Q47: (not in repo: MUSA5080-Final folder) | R47: ZORI 2015–2025 | S47: via ZIP crosswalk | T47: Superseded by Dewey rental listings (tract-level).
A48: Core | B48: Private public data | C48: Redfin Housing Market Data Center | D48: Redfin | E48: Private company, public aggregate data | F48: United States | G48: ZIP, city, county, metro, state depending on product | H48: Public dashboards and downloadable files | I48: Weekly/monthly depending on product | J48: Prices, sales, listings, supply, demand, price drops, property types, investor and financing trends | K48: Feasibility; Observatory; Typology & Climate | L48: Region; date; property type | M48: https://www.redfin.com/news/data-center/ | N48: Coverage and definitions differ by product; cite Redfin methodology and do not assume access to listing-level records. | O48: Organizers' catalog | P48: Not yet | S48: via ZIP
A49: Useful | B49: Private public data | C49: Redfin Migration Patterns | D49: Redfin | E49: Private company, public aggregate data | F49: United States | G49: Metro / origin-destination trends | H49: Public dashboard and data download | I49: Periodic | J49: Search-based migration and household-flow proxy | K49: Observatory; Typology & Climate | L49: Origin metro; destination metro; date | M49: https://www.redfin.com/news/data-center/migration-patterns/ | N49: Based on Redfin.com search behavior, not a representative count of actual household moves. | O49: Organizers' catalog | P49: Not yet | S49: no | T49: Low priority.
A50: Core | B50: Private public data | C50: Realtor.com Residential Real Estate Data Library | D50: Realtor.com Economic Research | E50: Private company, public aggregate data | F50: United States | G50: ZIP, county, metro, state, nation | H50: Free CSV downloads | I50: Weekly/monthly | J50: Inventory, list prices, days on market, price reductions, demand/hotness | K50: Feasibility; Observatory; Typology & Climate | L50: ZIP; county/metro ID; date | M50: https://www.realtor.com/research/data/ | N50: MLS listing coverage varies; historical series can be revised and attribution is requested. | O50: Organizers' catalog | P50: Not yet | S50: via ZIP
A51: Useful | B51: Mortgage rates | C51: Primary Mortgage Market Survey | D51: Freddie Mac | E51: Government-sponsored enterprise; public data | F51: United States | G51: National weekly rate | H51: Public download / chart | I51: Weekly | J51: Mortgage-rate assumptions and affordability scenarios | K51: Feasibility; Observatory | L51: Week/date | M51: https://www.freddiemac.com/pmms | N51: National averages; actual borrower rates vary by credit, loan, points, and geography. | O51: Organizers' catalog | P51: Not relevant | S51: no | T51: National weekly rate.
A52: Useful | B52: Home prices | C52: FHFA House Price Index | D52: Federal Housing Finance Agency | E52: Public | F52: United States | G52: ZIP, county, metro, state and nation depending on series | H52: Downloads / API | I52: Quarterly/monthly | J52: Repeat-sales price trends and regional benchmarking | K52: Observatory; Feasibility | L52: Geography code; date | M52: https://www.fhfa.gov/data/hpi | N52: Index measures appreciation, not price levels; thin markets can be volatile. | O52: Organizers' catalog | P52: Verified, not ingested | R52: annual | S52: via crosswalk (2010 tracts) | T52: Only free tract-level appreciation index; many low-sales tracts blank (P1).
A53: Useful | B53: Opportunity & mobility | C53: Opportunity Atlas | D53: Opportunity Insights / U.S. Census Bureau | E53: Research nonprofit / public data | F53: United States | G53: Census tract | H53: Public download and map | I53: Periodic research release | J53: Long-run mobility, income, incarceration and other outcomes by childhood neighborhood | K53: Typology & Climate; Observatory | L53: Census tract GEOID | M53: https://www.opportunityatlas.org/ | N53: Historical cohort outcomes are not current neighborhood conditions and should not be used to rank people. | O53: Organizers' catalog | P53: Not yet | S53: via crosswalk | T53: 2010 tracts.
A54: Useful | B54: Community demand | C54: Allegheny County 311 / Pittsburgh 311 Requests | D54: City of Pittsburgh / WPRDC | E54: Public | F54: City of Pittsburgh | G54: Request / location | H54: Open download; CSV/API | I54: Frequent | J54: Resident-reported infrastructure, property, trash, street and neighborhood issues | K54: Observatory; Typology & Climate | L54: Request ID; coordinates; date | M54: https://data.wprdc.org/dataset/311-data | N54: Reporting propensity varies by neighborhood; requests are not verified incidence counts. | O54: Organizers' catalog | P54: Not yet | S54: via point | T54: P1 neighborhood-conditions signal.
A55: Useful | B55: Schools & services | C55: NCES School Locations and Characteristics | D55: National Center for Education Statistics | E55: Public | F55: United States | G55: School / district | H55: Downloads and GIS | I55: Annual | J55: Access to schools, enrollment, school type, service-area context | K55: Typology & Climate | L55: NCES school/district ID; coordinates | M55: https://nces.ed.gov/programs/edge/Geographic/SchoolLocations | N55: School quality should not be reduced to a single measure; attendance boundaries may require local data. | O55: Organizers' catalog | P55: In use | Q55: data/processed/opportunity_access.parquet | R55: CCD 2024–25 | S55: yes (distance) | T55: D2: nearest elementary/middle/high school (via Urban Institute Education Data API).
A56: Core | B56: Vacancy & distress | C56: Allegheny County Real Estate Tax Delinquency | D56: Allegheny County Treasurer | E56: Public | F56: Allegheny County | G56: Parcel | H56: Open download; CSV/API | I56: Weekly | J56: Fiscal disinvestment | L56: Parcel ID | M56: https://data.wprdc.org/dataset/delinquent-real-estate-taxes | O56: Organizers' catalog | P56: Verified, not ingested | S56: via parcel | T56: P1 distress signal.
A57: Core | B57: Vacancy & distress | C57: City of Pittsburgh and School District Property Tax Delinquency | D57: City of Pittsburgh | E57: Public | F57: City of Pittsburgh, Pittsburgh Public Schools | G57: Parcel | H57: Open download; CSV/API | I57: Weekly | J57: Fiscal disinvestment | L57: Parcel ID | M57: https://data.wprdc.org/dataset/city-of-pittsburgh-property-tax-delinquency | N57: Reflects current year | O57: Organizers' catalog | P57: Not yet | S57: via parcel
A58: Core | B58: Vacancy & distress | C58: Mortgage Foreclosures | D58: Allegheny County | E58: Public | F58: Allegheny County | G58: Parcel | H58: Open download; CSV/API | I58: Monthly | J58: Fiscal disinvestment | L58: Parcel ID | M58: https://data.wprdc.org/dataset/allegheny-county-mortgage-foreclosure-records | N58: Not all properties that receive a filing actually change hands through a foreclosure process. Data reflects that court filings exist in the docket. | O58: Organizers' catalog | P58: Not yet | S58: via parcel | T58: P1 distress signal.
A59: Core | B59: Vacancy & distress | C59: City-owned property | D59: City of Pittsburgh | E59: Public | F59: City of Pittsburgh | G59: Parcel | H59: Open download; CSV/API | I59: Daily | J59: Public ownership | L59: Parcel ID | M59: https://data.wprdc.org/dataset/city-owned-properties | O59: Organizers' catalog | P59: Verified, not ingested | S59: via parcel | T59: See City-Owned Properties.
A60: Useful | B60: Jobs & mobility | C60: Mercatus Commuter Market Access Dataset for Congested Auto Travel (McMADCAT) | D60: Mercatus Center, George Mason University | E60: Research center / public data | F60: 50 states and Washington, DC | G60: Census tract; five-minute travel-time bands | H60: Free ZIP downloads; summary and full data; PDF documentation | I60: Research release (2025 congested travel times) | J60: Map jobs reachable from homes and workers reachable from job sites by congested car travel; compare housing sites and labor-market access | K60: Typology & Climate; Observatory; Feasibility | L60: Census tract GEOID | M60: https://www.mercatus.org/commuter-market-access-dataset | N60: Auto only; 60-minute cutoff and tract-centroid travel times. Mostly 2023 LODES jobs (Michigan 2021; Alaska 2016); 2019–2023 ACS. Free use with attribution requested. | O60: Organizers' catalog | P60: Not yet
A61: Useful | B61: Jobs & mobility | C61: Access Across America | D61: University of Minnesota Accessibility Observatory / Center for Transportation Studies | E61: University research / public data | F61: United States; metro summaries focus on major metropolitan areas | G61: Census block access measures; metro summaries | H61: Public reports and data via University Digital Conservancy | I61: Annual series; 2024 data year available | J61: Compare access to jobs by auto, transit, biking, and walking; identify housing locations with strong multimodal opportunity access | K61: Typology & Climate; Observatory; Feasibility | L61: Census block GEOID; metro / year | M61: https://access.umn.edu/ao-research/aaa | N61: Mode, travel-time threshold, coverage and data availability vary by year/product. Verify the specific download and reuse terms in the Digital Conservancy; accessibility is modeled, not observed commutes. | O61: Organizers' catalog | P61: Not yet | S61: unknown
A62: Core | B62: Equity & vulnerability | C62: CDC/ATSDR Social Vulnerability Index 2022 | D62: CDC/ATSDR | E62: Public | F62: United States | G62: Tract | H62: CSV download | I62: Biennial | J62: Displacement-risk component (overall + 4 themes) | K62: Typology & Climate; Observatory | L62: GEOID | M62: https://svi.cdc.gov/Documents/Data/2022/csv/states/Pennsylvania.csv | N62: Ranks within PA (re-ranked county-wide); 12 Allegheny tracts missing. | O62: Added by VisionPitts | P62: In use | Q62: data/external/benchmark/svi/svi2022_pa.csv | R62: 2022 | S62: yes | T62: displacement_risk (weight 0.3).
A63: Core | B63: Housing market | C63: Reinvestment Fund Market Value Analysis 2021 | D63: Reinvestment Fund / URA / WPRDC | E63: Public | F63: Allegheny County | G63: Block group (2010) | H63: GeoJSON download | I63: ~5 years | J63: Market type A–J | K63: Typology & Climate; Observatory | L63: BG GEOID → tract crosswalk | M63: https://data.wprdc.org/dataset/market-value-analysis-2021 | N63: 2010 block groups; categories not comparable across vintages. | O63: Added by VisionPitts | P63: In use | Q63: data/external/benchmark/mva/mva2021.geojson | R63: 2021 | S63: via crosswalk | T63: market_strength (80%).
A64: Core | B64: Housing market | C64: Reinvestment Fund Market Value Analysis 2016 (County + City) | D64: Reinvestment Fund / URA / WPRDC | E64: Public | F64: Allegheny County | G64: Block group (2010) | H64: SHP download | I64: ~5 years | J64: Direction of market change 2016→2021 | K64: Typology & Climate | L64: BG GEOID → tract crosswalk | M64: https://data.wprdc.org/dataset/market-value-analysis-2016 | N64: Two separately calibrated models; direction only. | O64: Added by VisionPitts | P64: In use | Q64: data/external/benchmark/mva/ | R64: 2016 | S64: via crosswalk | T64: market_strength (20%); mva_trend arrow.
A65: Core | B65: Displacement | C65: Eviction Lab Eviction Tracking System — Pittsburgh (ZIP, monthly) | D65: Eviction Lab, Princeton | E65: Nonprofit research | F65: Allegheny County (145 ZIPs) | G65: ZIP × month | H65: CSV (S3) | I65: Monthly | J65: Recent eviction filing rate per tract | K65: Typology & Climate; Observatory | L65: ZIP → tract (renter units) | M65: https://eviction-lab-data-downloads.s3.amazonaws.com/ets/all_sites_monthly_2020_2021.csv | N65: Court filings, not evictions; 1.2% sealed; modeled ZIP→tract. | O65: Added by VisionPitts | P65: In use | Q65: data/processed/evictions.parquet | R65: 2024-09 → 2026-08 | S65: via ZIP spread | T65: D1: 382/394 tracts; standalone layer (not yet in displacement_risk).
A66: Useful | B66: Displacement | C66: Eviction Lab modeled tract filings 2000–2018 | D66: Eviction Lab | E66: Nonprofit research | F66: United States | G66: Tract (2010) | H66: CSV (S3) | I66: Static | J66: — | K66: Observatory | L66: GEOID (2010) | M66: https://eviction-lab-data-downloads.s3.amazonaws.com/estimating-eviction-prevalance-across-us/tract_proprietary_2000_2018.csv | N66: No Allegheny tract data after 2006 → unusable. | O66: Added by VisionPitts | P66: On disk (unused) | Q66: data/external/benchmark/eviction/ | R66: 2000–2018 | S66: no (empty) | T66: Replaced by ETS.
A67: Core | B67: Subsidized housing | C67: HUD Housing Choice Vouchers by Tract | D67: HUD | E67: Public | F67: United States | G67: Tract | H67: ArcGIS service | I67: Annual | J67: Voucher density (displacement component) | K67: Typology & Climate | L67: GEOID | M67: https://services.arcgis.com/VTyQ9soqVukalItT/arcgis/rest/services/Housing_Choice_Vouchers_by_Tract/FeatureServer/0 | N67: ≤10 holders suppressed (200 tracts null). | O67: Added by VisionPitts | P67: In use | Q67: data/external/benchmark/hcv/hcv_by_tract_42003.json | R67: to 12/2025 | S67: yes | T67: displacement_risk (weight 0.2).
A68: Core | B68: Subsidy eligibility | C68: HUD Qualified Census Tracts 2026 | D68: HUD | E68: Public | F68: United States | G68: Tract | H68: CSV zip | I68: Annual | J68: Subsidy flag | K68: Typology & Climate; Feasibility | L68: GEOID | M68: https://www.huduser.gov/portal/datasets/qct/QCT2026CSV.zip | O68: Added by VisionPitts | P68: In use | Q68: data/external/benchmark/flags/ | R68: 2026 | S68: yes | T68: 90 Allegheny tracts; subsidy_eligible.
A69: Core | B69: Subsidy eligibility | C69: HUD Small Area Difficult Development Areas 2026 | D69: HUD | E69: Public | F69: United States | G69: ZCTA | H69: XLSX | I69: Annual | J69: Subsidy flag | K69: Typology & Climate; Feasibility | L69: ZCTA → tract (area) | M69: https://www.huduser.gov/portal/datasets/qct/2026-DDAs-Data-Used-to-Designate.xlsx | N69: Area-overlap assignment. | O69: Added by VisionPitts | P69: In use | Q69: data/external/benchmark/flags/ | R69: 2026 | S69: via ZCTA | T69: 13 tracts.
A70: Core | B70: Subsidy eligibility | C70: Opportunity Zones | D70: CDFI Fund / HUD ArcGIS | E70: Public | F70: United States | G70: Tract (2010) | H70: ArcGIS service | I70: Static (2018) | J70: Subsidy flag | K70: Typology & Climate | L70: GEOID10 → 2020 crosswalk | M70: https://services.arcgis.com/VTyQ9soqVukalItT/arcgis/rest/services/Opportunity_Zones/FeatureServer/13 | N70: 2010 tracts; new round from 2027. | O70: Added by VisionPitts | P70: In use | Q70: data/external/benchmark/flags/oz_42003.json | R70: 2018 | S70: via crosswalk | T70: 61 tracts.
A71: Core | B71: Subsidy eligibility | C71: City of Pittsburgh CDBG-eligible block groups | D71: City of Pittsburgh / WPRDC | E71: Public | F71: City of Pittsburgh | G71: Block group (2010) | H71: CSV | I71: Periodic | J71: Subsidy flag | K71: Typology & Climate | L71: BG → tract (HU ≥50%) | M71: https://data.wprdc.org/datastore/dump/dc85da67-b32f-4408-acef-b763d08b5bf0 | N71: City only (null elsewhere); 2018 LMISD. | O71: Added by VisionPitts | P71: In use | Q71: data/external/benchmark/flags/cdbg2018_pgh_bg.csv | R71: 2018 | S71: via crosswalk | T71: 74 eligible tracts.
A72: Core | B72: Geographic reference | C72: Census 2010↔2020 relationship files (PA) | D72: U.S. Census Bureau | E72: Public | F72: Pennsylvania | G72: Tract / block group | H72: TXT | I72: Decennial | J72: 2010→2020 crosswalks | K72: All briefs | L72: GEOID | M72: https://www2.census.gov/geo/docs/maps-data/data/rel2020/ | N72: Area weights; HU weights built from 2020 blocks. | O72: Added by VisionPitts | P72: In use | Q72: data/interim/xwalk_*.parquet | R72: 2020 | S72: yes
A73: Useful | B73: Geographic reference | C73: City of Pittsburgh neighborhoods | D73: City of Pittsburgh / WPRDC | E73: Public | F73: City of Pittsburgh | G73: Neighborhood (90) | H73: GeoJSON | I73: Stable | J73: Labels, place search | K73: All briefs | L73: Spatial | M73: https://data.wprdc.org/dataset/e672f13d-71c4-4a66-8f38-710e75ed80a4 | O73: Added by VisionPitts | P73: In use | Q73: data/external/benchmark/neighborhoods/ | R73: current | S73: via area share | T73: Offline search index web/src/data/places.json.
A74: Core | B74: Buildings | C74: Overture Maps buildings | D74: Overture Maps Foundation | E74: Open data | F74: Global | G74: Building footprint | H74: GeoParquet (S3) | I74: Monthly | J74: 3D building extrusions in focus tracts | K74: Typology & Climate | L74: Spatial | M74: https://docs.overturemaps.org/guides/buildings/ | N74: Heights partial; filled from assessments STORIES. | O74: Added by VisionPitts | P74: In use | Q74: data/processed/buildings_focus.geojson | R74: 2026-09-23 | S74: yes | T74: 84% of heights from records.
A75: Useful | B75: Basemap & terrain | C75: Mapterhorn terrain tiles | D75: Mapterhorn | E75: Open data | F75: Global | G75: Raster tiles (~1 m at z16) | H75: Tile service | I75: Periodic | J75: 3D hills, hillshade, contours, cursor elevation | K75: Typology & Climate | L75: n/a | M75: https://tiles.mapterhorn.com | N75: Display only; attribution '© Mapterhorn'. | O75: Added by VisionPitts | P75: In use | Q75: (streamed in the web app) | R75: current | S75: n/a | T75: Falls back to AWS Terrarium.
A76: Useful | B76: Basemap & terrain | C76: OpenFreeMap basemap | D76: OpenFreeMap / OpenStreetMap | E76: Open data | F76: Global | G76: Vector tiles | H76: Tile service | I76: Weekly | J76: Keyless basemap + 3D context buildings | K76: All briefs | L76: n/a | M76: https://tiles.openfreemap.org/styles/positron | N76: OSM building heights mostly default in Pittsburgh. | O76: Added by VisionPitts | P76: In use | Q76: (streamed in the web app) | R76: current | S76: n/a
A77: Core | B77: Hazards & environment | C77: HAND flood screening share (MUSA 6950 research) | D77: VisionPitts research (USGS HAND) | E77: Derived | F77: Allegheny County | G77: Tract | H77: Parquet | I77: Static | J77: flood_exposure factor | K77: Typology & Climate | L77: GEOID | M77: research/musa6950_takeaway/ | N77: Screening model, not FEMA. | O77: Added by VisionPitts | P77: In use | Q77: data/processed/tract_ndvi_flood.parquet | R77: 2024 | S77: yes | T77: Validate against FEMA NFHL (P0).
A78: Core | B78: Housing market | C78: Dewey — Rental Listings (Pennsylvania) | D78: Dewey Data (scraped listings) | E78: Private, licensed | F78: Pennsylvania | G78: Listing point (lat/lon) | H78: Parquet (licensed download) | I78: Scrape-daily | J78: Asking rents by tract/year, growth, FMR gap | K78: Typology & Climate; Observatory | L78: Point-in-tract | M78: https://www.deweydata.io/ | N78: Asking rents, market-rate skew; growth partly new-luxury composition; licensed — do not redistribute raw rows. | O78: Added by VisionPitts | P78: In use | Q78: data/raw/dewey/rental-listings-pa/ → data/processed/asking_rents.parquet | R78: 2019 → 2026-08 | S78: yes | T78: D7: 13.7M PA rows, 2.62M Allegheny; county 2BR $1,100 (2019) → $1,495 (2026).
A79: Useful | B79: Housing market | C79: Dewey — Listing ↔ Property mapping | D79: Dewey Data | E79: Private, licensed | F79: United States | G79: Listing ID | H79: Parquet (licensed download) | I79: Periodic | J79: Recover pre-2023 unit IDs for dedupe | K79: Observatory | L79: ID | M79: https://www.deweydata.io/ | N79: IDs only (307M rows). | O79: Added by VisionPitts | P79: In use | Q79: data/raw/dewey/listing-and-property-mapping/ | R79: 2026-05 | S79: n/a | T79: Used by D7 v2.
A80: Useful | B80: Demographics & housing | C80: Census 2020 DHC block tenure (H4) | D80: U.S. Census Bureau | E80: Public | F80: United States | G80: Block | H80: API | I80: Decennial | J80: Renter-unit weights for ZIP→tract | K80: Typology & Climate | L80: Block GEOID | M80: https://api.census.gov/data/2020/dec/dhc | O80: Added by VisionPitts | P80: In use | Q80: data/external/evictions/ | R80: 2020 | S80: yes | T80: D1 weights.
A81: Useful | B81: Prices | C81: BLS CPI-U annual averages | D81: U.S. Bureau of Labor Statistics | E81: Public | F81: United States | G81: National | H81: API | I81: Monthly | J81: 2013→2023 real-dollar conversion | K81: Observatory | L81: Year | M81: https://www.bls.gov/cpi/ | O81: Added by VisionPitts | P81: In use | Q81: (constants in build_profile_change.py) | R81: 2013, 2023 | S81: n/a | T81: D8.
A82: Useful | B82: Schools & services | C82: Allegheny County school district boundaries | D82: Allegheny County / WPRDC | E82: Public | F82: Allegheny County | G82: School district (45) | H82: GeoJSON | I82: Periodic | J82: School district per tract | K82: Typology & Climate | L82: Spatial | M82: https://data.wprdc.org/dataset/allegheny-county-school-district-boundaries | O82: Added by VisionPitts | P82: In use | Q82: data/processed/opportunity_access.parquet | R82: current | S82: yes | T82: D2 school_district.
A83: Useful | B83: Geocoding | C83: US Census Geocoder (geographies) | D83: U.S. Census Bureau | E83: Public | F83: United States | G83: Address → tract | H83: API (JSONP) | I83: Live | J83: Address search returns tract GEOID | K83: All briefs | L83: Address | M83: https://geocoding.geo.census.gov | N83: Query text sent to Census. | O83: Added by VisionPitts | P83: In use | Q83: (live in the web app) | R83: Current benchmark | S83: yes
A84: Useful | B84: Geocoding | C84: Photon geocoder (komoot, OSM) | D84: komoot | E84: Open data | F84: Global | G84: Address / place | H84: API | I84: Live | J84: Search-as-you-type | K84: All briefs | L84: Point-in-tract | M84: https://photon.komoot.io | N84: Fair use; OSM ODbL. | O84: Added by VisionPitts | P84: In use | Q84: (live in the web app) | R84: live | S84: yes | T84: Nominatim is the Enter-only fallback.
A85: Core | B85: Zoning & policy | C85: Pittsburgh zoning overlays incl. Inclusionary Zoning (IZ-O) | D85: City of Pittsburgh DCP | E85: Public | F85: City of Pittsburgh | G85: Overlay polygon | H85: ArcGIS service | I85: As amended | J85: IZ flag, parking/height constraints | K85: Typology & Climate; Permit Navigator | L85: Spatial | M85: https://services1.arcgis.com/YZCmUqbcsUpOKfj7/arcgis/rest/services/PGHWebZoningOverlays/FeatureServer/0 | N85: Overlay types packed in one text field. | O85: Added by VisionPitts | P85: Verified, not ingested | S85: via area share | T85: P0; mandatory IZ in Lawrenceville, Bloomfield, Polish Hill, Oakland.
A86: Useful | B86: Land & development | C86: City parcels with vacancy / owner / zoning (ParcelsPublic) | D86: City of Pittsburgh | E86: Public | F86: City of Pittsburgh | G86: Parcel | H86: ArcGIS service | I86: Weekly | J86: Buildable and public-land supply per tract | K86: Feasibility; Typology & Climate | L86: Parcel PIN | M86: https://pghgishub-pittsburghpa.opendata.arcgis.com | O86: Added by VisionPitts | P86: Verified, not ingested | R86: 2026-09-21 | S86: via parcel | T86: P0: ~31.8k vacant parcels (11,375 City-owned, 1,274 URA).
A87: Useful | B87: Land & development | C87: City historic districts | D87: City of Pittsburgh / WPRDC | E87: Public | F87: City of Pittsburgh | G87: Polygon | H87: GeoJSON | I87: Periodic | J87: Design-review friction layer | K87: Feasibility | L87: Spatial | M87: https://data.wprdc.org/dataset/8f92ae09-4cfa-4e0d-9c46-779a66d93d1e/resource/c926cfe2-e085-4808-94bc-b33895089a74/download/historic_districts.geojson | O87: Added by VisionPitts | P87: Verified, not ingested | S87: via area share | T87: P1.
A88: Useful | B88: Land & development | C88: City ETHOS lot suitability | D88: City of Pittsburgh | E88: Public | F88: City of Pittsburgh | G88: Parcel | H88: ArcGIS service | I88: Periodic | J88: Validate against the City's own view | K88: Feasibility | L88: Parcel | M88: https://services1.arcgis.com/YZCmUqbcsUpOKfj7/arcgis/rest/services/ETHOS_Lot_Suitability/FeatureServer/0 | O88: Added by VisionPitts | P88: Verified, not ingested | S88: via parcel | T88: P1.
A89: Core | B89: Hazards & environment | C89: Landslide-prone areas (City) + Pomeroy study (County) | D89: City of Pittsburgh / Allegheny County / WPRDC | E89: Public | F89: City + County | G89: Polygon | H89: GeoJSON | I89: Static | J89: Constraint share per tract | K89: Feasibility; Typology & Climate | L89: Spatial | M89: https://data.wprdc.org/dataset/landslide-prone-areas | N89: Pomeroy study is older. | O89: Added by VisionPitts | P89: Verified, not ingested | S89: via area share | T89: P0.
A90: Useful | B90: Trees & parks | C90: City street tree inventory | D90: City of Pittsburgh / WPRDC | E90: Public | F90: City of Pittsburgh | G90: Tree point (45,709) | H90: CSV/GeoJSON | I90: Periodic | J90: Tract tree counts and i-Tree $ benefits | K90: Typology & Climate | L90: Point-in-tract | M90: https://data.wprdc.org/dataset/city-trees | N90: City only. | O90: Added by VisionPitts | P90: Verified, not ingested | S90: via point | T90: P0 guide stat.
A91: Useful | B91: Trees & parks | C91: City Steps | D91: City of Pittsburgh / WPRDC | E91: Public | F91: City of Pittsburgh | G91: Point (1,134) | H91: GeoJSON | I91: Periodic | J91: Signature map layer with photos | K91: Typology & Climate | L91: Point-in-tract | M91: https://data.wprdc.org/dataset/city-steps | O91: Added by VisionPitts | P91: Verified, not ingested | S91: via point | T91: P0 basemap.
A92: Useful | B92: Trees & parks | C92: Parks, trails and greenways | D92: City of Pittsburgh / Allegheny County / WPRDC | E92: Public | F92: City + County | G92: Polygon / line | H92: GeoJSON | I92: Periodic | J92: Park access and basemap richness | K92: Typology & Climate | L92: Spatial | M92: https://data.wprdc.org/dataset/pittsburgh-trails | O92: Added by VisionPitts | P92: Verified, not ingested | S92: via spatial | T92: P0/P1.
A93: Useful | B93: Topography & imagery | C93: PEMA 2021–23 imagery tiles | D93: PEMA / PASDA | E93: Public | F93: Pennsylvania | G93: Raster tiles | H93: Tile service | I93: Periodic | J93: Keyless satellite toggle | K93: All briefs | L93: n/a | M93: https://imagery.pasda.psu.edu/arcgis/rest/services/PEMAImagery2021_2023cache/MapServer/tile/{z}/{y}/{x} | O93: Added by VisionPitts | P93: Verified, not ingested | R93: 2021–23 | S93: n/a | T93: P0 (web only).
A94: Core | B94: Subsidized housing | C94: HUD Public Housing Developments | D94: HUD | E94: Public | F94: United States | G94: Development point | H94: ArcGIS service | I94: Periodic | J94: Existing affordable stock | K94: Typology & Climate; Observatory | L94: Point-in-tract | M94: https://services.arcgis.com/VTyQ9soqVukalItT/arcgis/rest/services/Public_Housing_Developments/FeatureServer/0 | O94: Added by VisionPitts | P94: Verified, not ingested | S94: via point | T94: P0: 82 developments.
A95: Useful | B95: Subsidized housing | C95: HUD Picture of Subsidized Households (tract) | D95: HUD | E95: Public | F95: United States | G95: Tract | H95: XLSX | I95: Annual | J95: Subsidized households by program; expiring contracts | K95: Typology & Climate | L95: GEOID | M95: https://www.huduser.gov/portal/datasets/assthsg.html | O95: Added by VisionPitts | P95: Verified, not ingested | R95: 2025 | S95: yes | T95: P1 (incl. 202 senior stock).
A96: Useful | B96: Health | C96: CDC PLACES 2025 (tract) | D96: CDC | E96: Public | F96: United States | G96: Tract | H96: Socrata API | I96: Annual | J96: Health and social-needs panel | K96: Typology & Climate | L96: GEOID | M96: https://data.cdc.gov/500-Cities-Places/PLACES-Census-Tract-Data-GIS-Friendly-Format-2025-/yjkw-uj5s | N96: Modeled estimates. | O96: Added by VisionPitts | P96: Verified, not ingested | R96: 2025 | S96: yes | T96: P0: 382/394 match.
A97: Useful | B97: Schools & services | C97: WPRDC Allegheny County Assets | D97: WPRDC | E97: Public (CC0) | F97: Allegheny County | G97: Point (32,001) | H97: CSV | I97: Periodic | J97: Pharmacies, supermarkets, health, senior centers, libraries, childcare | K97: Typology & Climate | L97: Point-in-tract | M97: https://data.wprdc.org/dataset/allegheny-county-assets | O97: Added by VisionPitts | P97: Verified, not ingested | S97: via point | T97: P0; better childcare coverage than OSM.
A98: Useful | B98: Schools & services | C98: PA child-care providers (OCDEL) | D98: PA Office of Child Development and Early Learning | E98: Public | F98: Pennsylvania | G98: Provider point (718 in Allegheny) | H98: Socrata API | I98: Monthly | J98: Early-childhood access | K98: Typology & Climate | L98: Point-in-tract | M98: https://data.pa.gov/Services-Near-You/Child-Care-Providers-including-Early-Learning-Prog/ajn5-kaxt | O98: Added by VisionPitts | P98: Verified, not ingested | S98: via point | T98: P0.
A99: Useful | B99: Schools & services | C99: Future Ready PA Index (school/district performance) | D99: PA Department of Education | E99: Public | F99: Pennsylvania | G99: School / district | H99: XLSX | I99: Annual | J99: Official school measures (Niche replacement) | K99: Typology & Climate | L99: AUN + school no. | M99: https://futurereadypa.org/Home/DataFiles | N99: No composite grade by design; show beside % economically disadvantaged. | O99: Added by VisionPitts | P99: Verified, not ingested | R99: 2024–25 | S99: via school | T99: P0. Niche is link-out only (terms bar scraping).
A100: Useful | B100: Schools & services | C100: Pittsburgh Public Schools feeder boundaries | D100: PPS / WPRDC | E100: Public | F100: City of Pittsburgh | G100: Attendance polygon | H100: SHP zip | I100: Stale | J100: Assigned schools per city tract | K100: Typology & Climate | L100: Spatial | M100: https://data.wprdc.org/dataset/pittsburgh-public-schools-feeder-pattern-attendance-boundaries | N100: SY2012-13 boundaries; confirm with PPS. | O100: Added by VisionPitts | P100: Verified, not ingested | R100: 2012–13 | S100: via spatial | T100: P0 with caveat.
...

Sheet Read Me
A1: AI Hackathon for Housing — Public Data Catalog
A3: Purpose | B3: A curated starting point for Pittsburgh and Allegheny County hackathon teams. It prioritizes sources that can support parcel feasibility, permitting, housing-market observatories, typology matching, equity, and climate analysis.
A4: Core vs. Useful | B4: Core sources are likely to support a central prototype workflow. Useful sources add context, validation, or specialized features.
A5: Public does not mean unrestricted | B5: Review the terms, attribution requirements, API limits, and licenses before downloading, redistributing, or publishing derived data.
A6: Private-company public data | B6: Zillow, Redfin, and Realtor.com rows refer to their public aggregate research datasets—not listing-level feeds, property APIs, or permission to scrape their consumer websites.
A7: Geographic joins | B7: Prefer stable identifiers: parcel ID for local property records and Census GEOID/FIPS for statistical geography. Keep a crosswalk when vintages differ.
A8: Quality rule | B8: Record the download date, source vintage, field definitions, missingness, revisions, and any transformations. Never let an AI-generated answer outrank an authoritative rule or source record.
A9: Privacy rule | B9: Do not publish person-level tenant, applicant, mortgage, or household data. Aggregate, suppress small cells, and document consent for contributed data.
A10: VisionPitts master list | B10: Extended by the VisionPitts team (Track 3) on 2026-09-26. The organizers' 60 rows are unchanged in columns A–N. Columns O–T record our status, and rows below the original list are sources VisionPitts added.
A11: VisionPitts columns | B11: Origin · VisionPitts status · Local path / output · Vintage in use · Tract-level? · VisionPitts notes. See the 'VisionPitts Summary' sheet for counts and the status key.

Sheet Brief Source Map
A1: Problem brief | B1: Start with these core sources | C1: High-value additions
A2: Development Feasibility & Pro Forma Navigator | B2: County assessments, sales and parcels; Pittsburgh zoning code/map; PLI permits; OneStopPGH; FEMA flood layer; steep slopes; undermined areas | C2: PASDA/USGS elevation and imagery; BLS PPI; HUD income limits/FMR; Zillow, Redfin and Realtor.com aggregate markets
A3: Policy-to-Permit Navigator | B3: Pittsburgh zoning code; PLI permits; OneStopPGH; ZBA decisions; municipal codes | C3: Violations; condemned properties; cross-jurisdiction county GIS; historical permits
A4: Housing Production, Rents & Household Flow Observatory | B4: PLI permits; ACS; Decennial Census; CHAS; county sales; Zillow ZORI/ZHVI; Redfin; Realtor.com | C4: USPS vacancy; LIHTC/NHPD; HMDA; LODES; Redfin migration; 311
A5: Housing Typology, Equity & Climate Matchmaker | B5: ACS; CHAS; parcels/land use/zoning; PRT GTFS; LAI; FEMA; slopes; ResStock | C5: Opportunity Atlas; EPA EJScreen; NLCD; NOAA; schools; market-demand datasets

Sheet VisionPitts Layers
A1: Layer | B1: File | C1: Roadmap item | D1: Rows | E1: Key columns | F1: Sources | G1: Confidence | H1: How the dashboard uses it | I1: Status
A2: Tract factors (scored) | B2: data/tracts.geojson → web/src/data/tracts.json | C2: Core | D2: 394 | E2: need, market_strength, displacement_risk, subsidy_eligible, transit_access, flood_exposure (+ _conf) | F2: CHAS, MVA, SVI, HCV, QCT/DDA/OZ/CDBG, GTFS, HAND | G2: Per factor | H2: Scoring, map, factor cards | I2: In dashboard
A3: ACS context | B3: data/processed/tracts_acs.parquet | C3: Core | D3: 394 | E3: pop, med_hh_income, med_gross_rent, renter_share, rent_burdened_share (+ CV) | F3: ACS 2020–24 | G3: CV-based | H3: Tract panel 'About this place' | I3: In dashboard
A4: Terrain | B4: data/processed/tract_terrain.parquet | C4: Core | D4: 394 | E4: elev_mean/min/max/range_ft, slope_mean_pct, steep15/25_share | F4: USGS 3DEP | G4: Info only | H4: Terrain card, Elevation/Steep layers | I4: In dashboard
A5: Evictions | B5: data/processed/evictions.parquet | C5: D1 | D5: 394 | E5: eviction_filing_rate, eviction_filing_rate_dhc20, eviction_vs_baseline, evictions_conf | F5: Eviction Lab ETS, Census DHC | G5: Medium/low | H5: Card + map; not yet in displacement_risk (decision pending) | I5: Built, not wired
A6: Market pressure | B6: data/processed/market_pressure.parquet | C6: D3 | D6: 394 | E6: pressure_lag, pressure_class, mva_trend, bivar_class, watch_list, no_rec, lisa_cluster, flip_bal_anti | F6: MVA, CHAS, scoring engine | G6: Low (screening) | H6: One 'Market pressure' map + watch list (58 tracts) | I6: Built, not wired
A7: Income limits & FMR | B7: web/src/data/income_limits.json | C7: D4 | D7: metro | E7: mfi, il30/il50/il80 (1–8 persons), fmr 0–4BR, affordable_rent_50ami | F7: HUD FY2026 | G7: High | H7: Dollar line on landing and tract panel | I7: Built, not wired
A8: Neighborhood change | B8: data/processed/profile_change.parquet | C8: D8 | D8: 394 | E8: <var>_2013/_2023/_chg/_chg_sig for 13 variables | F8: ACS 2009–13, 2019–23, BLS CPI | G8: Medium | H8: 'Ten-year change' section | I8: Built, not wired
A9: Permits & demolitions | B9: data/processed/permits.parquet, permits_by_year.parquet | C9: D8 | D9: 394 | E9: permits_newres_<year>, permits_demo_<year>, totals | F9: City PLI permits | G9: Medium (city only) | H9: Bar chart on tract card | I9: Built, not wired
A10: Opportunity access | B10: data/processed/opportunity_access.parquet | C10: D2 | D10: 394 | E10: jobs_3km_*, school_nearest_*, school_district, svc_*_800m, nearest_supermarket_m | F10: LODES 2023, NCES CCD 2024–25, OSM | G10: Per part | H10: 'Access' section (jobs · schools · services) | I10: Built, not wired
A11: Asking rents | B11: data/processed/asking_rents.parquet + asking_rents_county.json | C11: D7 | D11: 394 | E11: rent_2br_<year>, rent_2br_2025_26, rent_2br_growth_2019_2026, rent_2br_gt_fmr, rent_index_* | F11: Dewey rental listings | G11: High/medium/low by n | H11: Rent card, growth map, FMR gap line | I11: Built, not wired
A12: 3D buildings | B12: data/processed/buildings_focus.geojson → web/src/data/buildings.json | C12: Core | D12: 7,588 bldgs | E12: h, src, yb | F12: Overture, parcels, assessments | G12: 84% heights from records | H12: 3D extrusions in focus tracts | I12: In dashboard
A13: Place search index | B13: data/processed/places.json → web/src/data/places.json | C13: Core | D13: 244 | E13: n, k, c, b, g | F13: WPRDC neighborhoods, Census county subdivisions | G13: n/a | H13: Offline search | I13: In dashboard
